mission_control/__init__.py
mission_control/__main__.py
mission_control/alert_finder.py
mission_control/cli.py
mission_control/models.py
mission_control/output_formatter.py
mission_control/telemetry_file_parser.py
mission_control/telemetry_processor.py
tests/__init__.py
tests/test_alert_finder.py
tests/test_cli.py
tests/test_output_formatter.py
tests/test_telemetry_file_parser.py
tests/test_telemetry_processor.py
arvind_mission_control-0.0.7.dist-info/LICENSE
arvind_mission_control-0.0.7.dist-info/METADATA
arvind_mission_control-0.0.7.dist-info/WHEEL
arvind_mission_control-0.0.7.dist-info/entry_points.txt
arvind_mission_control-0.0.7.dist-info/top_level.txt
arvind_mission_control-0.0.7.dist-info/RECORD
